graphene_pydantic_fix/__init__.py
graphene_pydantic_fix/converters.py
graphene_pydantic_fix/registry.py
graphene_pydantic_fix/types.py
graphene_pydantic_fix/util.py
graphene_pydantic_fix-0.0.6.dist-info/LICENSE.md
graphene_pydantic_fix-0.0.6.dist-info/WHEEL
graphene_pydantic_fix-0.0.6.dist-info/METADATA
graphene_pydantic_fix-0.0.6.dist-info/RECORD
