Metadata-Version: 2.1
Name: graphene-pydantic-fix
Version: 0.0.6
Summary: Graphene Pydantic integration
Home-page: https://github.com/Mc01/graphene-pydantic
License: Apache-2.0
Keywords: api,graphql,protocol,rest,relay,graphene,pydantic,model
Author: Rami Chowdhury
Author-email: rami@upside.com
Requires-Python: >=3.6,<4.0
Classifier: Development Status :: 3 - Alpha
Classifier: Intended Audience :: Developers
Classifier: License :: OSI Approved :: Apache Software License
Classifier: Programming Language :: Python :: 3
Classifier: Programming Language :: Python :: 3.6
Classifier: Programming Language :: Python :: 3.7
Classifier: Programming Language :: Python :: 3.8
Classifier: Programming Language :: Python :: Implementation :: PyPy
Classifier: Topic :: Software Development :: Libraries
Requires-Dist: graphene (>=2.1.3,<3)
Requires-Dist: pydantic (>=0.26,<=1.4)
Project-URL: Repository, https://github.com/Mc01/graphene-pydantic
